jugg/__init__.py
jugg/client.py
jugg/constants.py
jugg/core.py
jugg/security.py
jugg/server.py
jugg/utils.py
jugg-1.1.8.dist-info/DESCRIPTION.rst
jugg-1.1.8.dist-info/METADATA
jugg-1.1.8.dist-info/RECORD
jugg-1.1.8.dist-info/WHEEL
jugg-1.1.8.dist-info/metadata.json
jugg-1.1.8.dist-info/top_level.txt
