Metadata-Version: 2.0
Name: jugg
Version: 1.1.8
Summary: A secure, end-to-end encrypted communication framework
Home-page: https://github.com/zachgates/jugg
Author: Zach Gates
Author-email: thezachgates@gmail.com
License: MIT
Platform: UNKNOWN
Classifier: License :: OSI Approved :: MIT License
Classifier: Programming Language :: Python :: 3
Classifier: Programming Language :: Python :: 3.3
Classifier: Programming Language :: Python :: 3.4
Classifier: Programming Language :: Python :: 3.5
Classifier: Programming Language :: Python :: 3.6
Requires-Dist: pyarchy
Requires-Dist: pycryptodome
Requires-Dist: srp
